third_eye_mcp/__init__.py
third_eye_mcp/__main__.py
third_eye_mcp/server.py
third_eye_mcp/types.py
third_eye_mcp/services/__init__.py
third_eye_mcp/services/ads.py
third_eye_mcp/services/recording.py
third_eye_mcp/services/recording_storage.py
third_eye_mcp/services/screenshot.py
third_eye_mcp/services/storage.py
third_eye_mcp/services/watermark.py
third_eye_mcp/tools/__init__.py
third_eye_mcp/tools/capture.py
third_eye_mcp/tools/capture_region.py
third_eye_mcp/tools/get_frame.py
third_eye_mcp/tools/latest.py
third_eye_mcp/tools/list_displays.py
third_eye_mcp/tools/record.py
third_eye_mcp/tools/scheduled_record.py
third_eye_mcp-1.1.1.dist-info/METADATA
third_eye_mcp-1.1.1.dist-info/WHEEL
third_eye_mcp-1.1.1.dist-info/entry_points.txt
third_eye_mcp-1.1.1.dist-info/licenses/LICENSE
third_eye_mcp-1.1.1.dist-info/RECORD
