Metadata-Version: 2.4
Name: third-eye-mcp
Version: 1.1.1
Summary: Free MCP server for screen capture and recording with promotional ads
Project-URL: Homepage, https://grandnasser.com/third-eye
Project-URL: Repository, https://github.com/Osseni94/third-eye-mcp
Author-email: Kaossara Osseni <admin@grandnasser.com>
License-Expression: MIT
License-File: LICENSE
Keywords: mcp,model-context-protocol,screen-capture,screen-recording,screenshot
Classifier: Development Status :: 4 - Beta
Classifier: Intended Audience :: Developers
Classifier: License :: OSI Approved :: MIT License
Classifier: Programming Language :: Python :: 3
Classifier: Programming Language :: Python :: 3.10
Classifier: Programming Language :: Python :: 3.11
Classifier: Programming Language :: Python :: 3.12
Requires-Python: >=3.10
Requires-Dist: mcp>=1.0.0
Requires-Dist: mss>=9.0.0
Requires-Dist: pillow>=10.0.0
Requires-Dist: pydantic>=2.0.0
